toponetx/__init__.py
toponetx/_version.py
toponetx/exception.py
toponetx/algorithms/__init__.py
toponetx/algorithms/components.py
toponetx/algorithms/distance.py
toponetx/algorithms/distance_measures.py
toponetx/algorithms/spectrum.py
toponetx/algorithms/exterior_calculus/__init__.py
toponetx/algorithms/exterior_calculus/exterior_calc.py
toponetx/algorithms/exterior_calculus/metric.py
toponetx/classes/.DS_Store
toponetx/classes/__init__.py
toponetx/classes/cell.py
toponetx/classes/cell_complex.py
toponetx/classes/colored_hypergraph.py
toponetx/classes/combinatorial_complex.py
toponetx/classes/complex.py
toponetx/classes/hyperedge.py
toponetx/classes/path.py
toponetx/classes/path_complex.py
toponetx/classes/reportviews.py
toponetx/classes/simplex.py
toponetx/classes/simplex_trie.py
toponetx/classes/simplicial_complex.py
toponetx/datasets/.gitignore
toponetx/datasets/__init__.py
toponetx/datasets/ahorn.py
toponetx/datasets/benson.py
toponetx/datasets/graph.py
toponetx/datasets/mesh.py
toponetx/datasets/utils.py
toponetx/generators/__init__.py
toponetx/generators/classic_cell_complexes.py
toponetx/generators/random_cell_complexes.py
toponetx/generators/random_simplicial_complexes.py
toponetx/readwrite/__init__.py
toponetx/readwrite/atomlist.py
toponetx/readwrite/serialization.py
toponetx/transform/__init__.py
toponetx/transform/delaunay.py
toponetx/transform/graph_to_cell_complex.py
toponetx/transform/graph_to_simplicial_complex.py
toponetx/utils/__init__.py
toponetx/utils/iterable.py
toponetx/utils/normalization.py
toponetx/utils/structure.py
toponetx-0.4.0.dist-info/licenses/LICENSE.txt
toponetx-0.4.0.dist-info/METADATA
toponetx-0.4.0.dist-info/WHEEL
toponetx-0.4.0.dist-info/top_level.txt
toponetx-0.4.0.dist-info/RECORD
