Metadata-Version: 2.4
Name: TopoNetX
Version: 0.4.0
Summary: Computing on Topological Domains
Author-email: Mustafa Hajij <mhajij@usfca.edu>, Mathilde Papillon <papillon@ucsb.edu>, Florian Frantzen <frantzen@netsci.rwth-aachen.de>
License: Copyright (c) 2022 pyt-team authors
Project-URL: documentation, https://pyt-team.github.io/toponetx/
Project-URL: source, https://github.com/pyt-team/TopoNetX/
Classifier: Development Status :: 3 - Alpha
Classifier: Intended Audience :: Developers
Classifier: Intended Audience :: Science/Research
Classifier: Operating System :: OS Independent
Classifier: License :: OSI Approved :: MIT License
Classifier: Programming Language :: Python :: 3
Classifier: Programming Language :: Python :: 3 :: Only
Classifier: Programming Language :: Python :: 3.12
Classifier: Programming Language :: Python :: 3.13
Classifier: Programming Language :: Python :: 3.14
Classifier: Topic :: Scientific/Engineering
Classifier: Topic :: Scientific/Engineering :: Mathematics
Classifier: Topic :: Scientific/Engineering :: Artificial Intelligence
Requires-Python: !=3.14.1,>=3.12
License-File: LICENSE.txt
Requires-Dist: more-itertools>=10.7.0
Requires-Dist: networkx
Requires-Dist: numpy
Requires-Dist: pandas
Requires-Dist: pyarrow
Requires-Dist: requests
Requires-Dist: scipy
Requires-Dist: trimesh
Requires-Dist: typing-extensions
Provides-Extra: all
Requires-Dist: ahorn-loader>=0.2.0; extra == "all"
Requires-Dist: hypernetx~=2.3; extra == "all"
Requires-Dist: spharapy; extra == "all"
Dynamic: license-file
